CHANGELOG.md
LICENSE
README.md
picopins/__init__.py
picopins/__main__.py
picopins-1.2.0.dist-info/METADATA
picopins-1.2.0.dist-info/WHEEL
picopins-1.2.0.dist-info/entry_points.txt
picopins-1.2.0.dist-info/licenses/LICENSE
picopins-1.2.0.dist-info/RECORD
