Metadata-Version: 2.1
Name: picopins
Version: 1.2.0
Summary: A command-line pinout for the Raspberry Pi Pico W
Project-URL: GitHub, https://www.github.com/pinout-xyz/picopins
Project-URL: Homepage, https://pico.pinout.xyz
Author-email: Philip Howard <pinout@gadgetoid.com>
Maintainer-email: Philip Howard <pinout@gadgetoid.com>
License: MIT License
License-File: LICENSE
Keywords: Pico,Raspberry
Classifier: Development Status :: 4 - Beta
Classifier: Intended Audience :: Developers
Classifier: License :: OSI Approved :: MIT License
Classifier: Operating System :: POSIX :: Linux
Classifier: Programming Language :: Python :: 3
Classifier: Programming Language :: Python :: 3 :: Only
Classifier: Programming Language :: Python :: 3.7
Classifier: Programming Language :: Python :: 3.8
Classifier: Programming Language :: Python :: 3.9
Classifier: Programming Language :: Python :: 3.10
Classifier: Programming Language :: Python :: 3.11
Classifier: Topic :: Software Development
Classifier: Topic :: System :: Hardware
Requires-Python: >=3.7
Requires-Dist: rich>=13.3.5
